{
    "type": "minecraft:crafting_shapeless",
    "ingredients": [
        {
            "tag": "crafting:terracotta/not_pink"
        },
        {
            "tag": "crafting:terracotta/not_pink"
        },
        {
            "tag": "crafting:terracotta/not_pink"
        },
        {
            "tag": "crafting:terracotta/not_pink"
        },
        {
            "item": "minecraft:pink_dye"
        }
    ],
    "result": {
        "item": "minecraft:pink_terracotta",
        "count": 4
    },
    "group": "pink_terracotta"
}