{
    "type": "minecraft:crafting_shapeless",
    "ingredients": [
        {"tag": "better_dyeables:dye/default"},
        {"tag": "better_dyeables:wool"},
        {"tag": "better_dyeables:wool"},
        {"tag": "better_dyeables:wool"},
        {"tag": "better_dyeables:wool"},
        {"tag": "better_dyeables:wool"},
        {"tag": "better_dyeables:wool"},
        {"tag": "better_dyeables:wool"},
        {"tag": "better_dyeables:wool"}
    ],
    "result": {
        "item": "minecraft:wool",
        "count": 8
    },
    "group": "default_wool"
}