{
    "type": "minecraft:crafting_shapeless",
    "ingredients": [
        {
            "tag": "crafting:banner"
        },
        {
            "tag": "crafting:banner"
        },
        {
            "tag": "crafting:banner"
        },
        {
            "tag": "crafting:banner"
        },
        {
            "item": "minecraft:red_dye"
        },
        {
            "tag": "crafting:banner"
        },
        {
            "tag": "crafting:banner"
        }
    ],
    "result": {
        "item": "minecraft:red_banner",
        "count": 6
    },
    "group": "red_banner"
}