{
    "type": "minecraft:crafting_shapeless",
    "ingredients": [
        {
            "tag": "crafting:wool/not_gray"
        },
        {
            "tag": "crafting:wool/not_gray"
        },
        {
            "tag": "crafting:wool/not_gray"
        },
        {
            "tag": "crafting:wool/not_gray"
        },
        {
            "item": "minecraft:gray_dye"
        },
        {
            "tag": "crafting:wool/not_gray"
        },
        {
            "tag": "crafting:wool/not_gray"
        },
        {
            "tag": "crafting:wool/not_gray"
        }
    ],
    "result": {
        "item": "minecraft:gray_wool",
        "count": 7
    },
    "group": "gray_wool"
}